<Properties StartupConfiguration="{3106D2D6-EE93-0563-48E7-82DDB287A8BD}|">
  <MonoDevelop.Ide.ItemProperties.Assembly-CSharp PreferredExecutionTarget="Unity.Editor" />
  <MonoDevelop.Ide.Workbench ActiveDocument="Assets/SBPVP v.1.0/Scripts/DeadZone.cs">
    <Files>
      <File FileName="Assets/Scripts/PlayerContoll.cs" Line="1" Column="1" />
      <File FileName="Assets/Scripts/MainCamera.cs" Line="25" Column="2" />
      <File FileName="Assets/Car Script basic/Script/Dot_Truck_Controller.cs" Line="1" Column="1" />
      <File FileName="Assets/Scripts/CameraSplit.cs" Line="1" Column="1" />
      <File FileName="Assets/SBPVP v.1.0/Scripts/CarControlCS.cs" Line="45" Column="9" />
      <File FileName="Assets/SBPVP v.1.0/Scripts/VehicleCameraControl.cs" Line="8" Column="15" />
      <File FileName="Assets/Scripts/AutoMove.cs" Line="9" Column="24" />
      <File FileName="Assets/SBPVP v.1.0/Scripts/DeadZone.cs" Line="30" Column="44" />
      <File FileName="../../../Documents/Roll a Ball/Assets/Script/playerController.cs" Line="3" Column="1" />
    </Files>
  </MonoDevelop.Ide.Workbench>
  <MonoDevelop.Ide.Workspace ActiveConfiguration="Debug" />
  <MonoDevelop.Ide.DebuggingService.Breakpoints>
    <BreakpointStore />
  </MonoDevelop.Ide.DebuggingService.Breakpoints>
  <MonoDevelop.Ide.DebuggingService.PinnedWatches />
  <MultiItemStartupConfigurations />
</Properties>